<DOMSymbolItem xmlns:xsi="http://www.w3.org/2001/XMLSchema-instance" xmlns="http://ns.adobe.com/xfl/2008/" name="Shop/Smileys/Guy" itemID="4fb0a813-0000030f" symbolType="graphic" lastModified="1528051471">
  <timeline>
    <DOMTimeline name="Guy">
      <layers>
        <DOMLayer name="Layer 2" color="#9933CC" outline="true" useOutlineView="true" layerType="mask">
          <frames>
            <DOMFrame index="0" duration="69" keyMode="9728">
              <elements>
                <DOMShape>
                  <fills>
                    <FillStyle index="1">
                      <SolidColor color="#FFB700"/>
                    </FillStyle>
                  </fills>
                  <edges>
                    <Edge fillStyle1="1" edges="!640 0|640 1040!640 1040|0 1040!0 1040|0 0!0 0|640 0"/>
                  </edges>
                </DOMShape>
              </elements>
            </DOMFrame>
          </frames>
        </DOMLayer>
        <DOMLayer name="Layer 1" color="#4FFF4F" parentLayerIndex="0" current="true" isSelected="true">
          <frames>
            <DOMFrame index="0" duration="53" tweenType="motion" motionTweenSnap="true" keyMode="22017">
              <elements>
                <DOMSymbolInstance libraryItemName="GuySprite" symbolType="graphic" centerPoint3DX="864" centerPoint3DY="26" loop="loop">
                  <matrix>
                    <Matrix a="2" d="2"/>
                  </matrix>
                  <transformationPoint>
                    <Point x="432" y="13"/>
                  </transformationPoint>
                </DOMSymbolInstance>
              </elements>
            </DOMFrame>
            <DOMFrame index="53" duration="15" tweenType="motion" motionTweenSnap="true" keyMode="22017">
              <elements>
                <DOMSymbolInstance libraryItemName="GuySprite" symbolType="graphic" centerPoint3DX="-832" centerPoint3DY="26" loop="loop">
                  <matrix>
                    <Matrix a="2" d="2" tx="-1696"/>
                  </matrix>
                  <transformationPoint>
                    <Point x="432" y="13"/>
                  </transformationPoint>
                </DOMSymbolInstance>
              </elements>
            </DOMFrame>
            <DOMFrame index="68" tweenType="motion" motionTweenSnap="true" keyMode="22017">
              <elements>
                <DOMSymbolInstance libraryItemName="GuySprite" symbolType="graphic" centerPoint3DX="-1312" centerPoint3DY="26" loop="loop">
                  <matrix>
                    <Matrix a="2" d="2" tx="-2176"/>
                  </matrix>
                  <transformationPoint>
                    <Point x="432" y="13"/>
                  </transformationPoint>
                </DOMSymbolInstance>
              </elements>
            </DOMFrame>
          </frames>
        </DOMLayer>
      </layers>
    </DOMTimeline>
  </timeline>
</DOMSymbolItem>